mymol/__init__.py
mymol/data_utils.py
mymol/date_utils.py
mymol/db_utils.py
mymol/file_utils.py
mymol/general_utils.py
mymol/lists_dicts_utils.py
mymol/machinelearning_utils.py
mymol/math_utils.py
mymol/networking_utils.py
mymol/string_utils.py
mymol/test.py
mymol/text_utils.py
mymol-1.0.1.dist-info/licenses/LICENSE
mymol-1.0.1.dist-info/METADATA
mymol-1.0.1.dist-info/WHEEL
mymol-1.0.1.dist-info/top_level.txt
mymol-1.0.1.dist-info/RECORD
