Metadata-Version: 2.4
Name: mymol
Version: 1.0.1
Summary: Usefull things
Author-email: Arthur Kwak <arthur@katak.nl>
License: MIT
Requires-Python: >=3.8
License-File: LICENSE
Dynamic: license-file
